pubmed_pdf_downloader/__init__.py
pubmed_pdf_downloader/downloader.py
pubmed_pdf_downloader-0.1.1.dist-info/licenses/LICENSE
pubmed_pdf_downloader-0.1.1.dist-info/METADATA
pubmed_pdf_downloader-0.1.1.dist-info/WHEEL
pubmed_pdf_downloader-0.1.1.dist-info/entry_points.txt
pubmed_pdf_downloader-0.1.1.dist-info/top_level.txt
pubmed_pdf_downloader-0.1.1.dist-info/RECORD
